decora_ble/__init__.py
decora_ble-0.2.0.dist-info/DESCRIPTION.rst
decora_ble-0.2.0.dist-info/METADATA
decora_ble-0.2.0.dist-info/RECORD
decora_ble-0.2.0.dist-info/WHEEL
decora_ble-0.2.0.dist-info/metadata.json
decora_ble-0.2.0.dist-info/top_level.txt
