Metadata-Version: 2.0
Name: decora-ble
Version: 0.2.0
Summary: A Python module to interact with the Leviton Decora Dimmer via Bluetooth (BLE)
Home-page: https://github.com/lucapinello/pydecora_ble
Author: Luca Pinello
Author-email: UNKNOWN
License: MIT
Platform: UNKNOWN
Requires-Dist: bluepy
